TPUCameraManager/TPUCameraManager.py
TPUCameraManager/__init__.py
TPUCameraManager/gst.py
TPUCameraManager/gstreamer.py
TPUCameraManager_devingator-0.0.2.dist-info/LICENSE
TPUCameraManager_devingator-0.0.2.dist-info/METADATA
TPUCameraManager_devingator-0.0.2.dist-info/WHEEL
TPUCameraManager_devingator-0.0.2.dist-info/top_level.txt
TPUCameraManager_devingator-0.0.2.dist-info/RECORD
